setup.py
tests/__init__.py
tests/test_utils.py
zwb_utils/__init__.py
zwb_utils/email.py
zwb_utils.egg-info/PKG-INFO
zwb_utils.egg-info/SOURCES.txt
zwb_utils.egg-info/dependency_links.txt
zwb_utils.egg-info/top_level.txt