Metadata-Version: 1.0
Name: zwb-utils
Version: 1.0.2
Summary: zwb_utils
Home-page: https://github.com/weibin268/zwb_utils
Author: zhuang weibin
Author-email: 448075543@qq.com
License: UNKNOWN
Keywords: util
Platform: any
